candies/__init__.py
candies/_version.py
candies/app.py
candies/base.py
candies/features.py
candies/interfaces.py
candies/utilities.py
candies-0.1.1.dist-info/LICENSE
candies-0.1.1.dist-info/METADATA
candies-0.1.1.dist-info/WHEEL
candies-0.1.1.dist-info/entry_points.txt
candies-0.1.1.dist-info/top_level.txt
candies-0.1.1.dist-info/RECORD
