Metadata-Version: 2.1
Name: candies
Version: 0.1.1
Summary: "Sweet, sweet candy-dates!"
Author: "Ujjwal Panda"
Author-email: "ujjwalpanda97@gmail.com"
License: MIT License
Project-URL: Home Page, https://github.com/astrogewgaw/candies
Project-URL: Source Code, https://github.com/astrogewgaw/candies
Project-URL: Documentation, https://github.com/astrogewgaw/candies
Project-URL: Bug Reports, https://github.com/astrogewgaw/candies/issues
Classifier: Operating System :: Unix
Classifier: Programming Language :: Python :: 3.8
Classifier: Programming Language :: Python :: 3.9
Classifier: Programming Language :: Python :: 3.10
Classifier: Programming Language :: Python :: 3.11
Classifier: License :: OSI Approved :: MIT License
Classifier: Topic :: Scientific/Engineering :: Astronomy
Requires-Python: >=3.8
License-File: LICENSE
Requires-Dist: numpy<2.0
Requires-Dist: rich
Requires-Dist: h5py
Requires-Dist: numba
Requires-Dist: priwo
Requires-Dist: pandas
Requires-Dist: cyclopts
Requires-Dist: generalimport
Requires-Dist: typing-extensions; python_version < "3.11"
